aws_policy_generator/__init__.py
aws_policy_generator/args_generator.py
aws_policy_generator/auto_shortener.py
aws_policy_generator/mappings.py
aws_policy_generator/safe_minimizer.py
aws_policy_generator/yaml_generator.py
aws_policy_generator/_internal/__init__.py
aws_policy_generator/_internal/argparser.py
aws_policy_generator/_internal/main.py
aws_policy_generator-1.4.0.dist-info/LICENSE
aws_policy_generator-1.4.0.dist-info/METADATA
aws_policy_generator-1.4.0.dist-info/WHEEL
aws_policy_generator-1.4.0.dist-info/entry_points.txt
aws_policy_generator-1.4.0.dist-info/top_level.txt
aws_policy_generator-1.4.0.dist-info/RECORD
