Metadata-Version: 2.1
Name: aws-policy-generator
Version: 1.4.0
Summary: AWS IAM Policy generator
Home-page: https://github.com/jtyers/aws-policy-generator
Author: Jonny Tyers
Author-email: jonny@jonnytyers.co.uk
License: MIT
Platform: UNKNOWN
Classifier: License :: OSI Approved :: MIT License
Classifier: Programming Language :: Python :: 3
Classifier: Programming Language :: Python :: 3.9
Classifier: Programming Language :: Python :: 3.10
License-File: LICENSE
Requires-Dist: aws-iam-utils (>=1.8.0)
